[{"type":"variableUpdate","id":"14eb366a-343b-11f1-89ad-92ec3147fd6f","processDefinitionKey":"DrugBatches","processDefinitionId":"DrugBatches:4:c6d55d1c-3422-11f1-89ad-92ec3147fd6f","processInstanceId":"d345f1e6-343a-11f1-89ad-92ec3147fd6f","activityInstanceId":"meetRegulationCondition:14eac138-343b-11f1-89ad-92ec3147fd6f","executionId":"d345f1e6-343a-11f1-89ad-92ec3147fd6f","caseDefinitionKey":null,"caseDefinitionId":null,"caseInstanceId":null,"caseExecutionId":null,"taskId":null,"tenantId":null,"userOperationId":null,"time":"2026-04-09T19:39:38.387+0200","removalTime":null,"rootProcessInstanceId":"d345f1e6-343a-11f1-89ad-92ec3147fd6f","variableName":"conditionResult","variableInstanceId":"14eb3669-343b-11f1-89ad-92ec3147fd6f","variableType":"String","value":"yes","valueInfo":{},"initial":false,"revision":0,"errorMessage":null}]